hwpx/__init__.py
hwpx/hi.py
hwpx-1.1.1.dist-info/licenses/LICENSE
hwpx-1.1.1.dist-info/METADATA
hwpx-1.1.1.dist-info/WHEEL
hwpx-1.1.1.dist-info/top_level.txt
hwpx-1.1.1.dist-info/RECORD
