Metadata-Version: 2.4
Name: hwpx
Version: 1.1.1
Summary: the lightweight hwp automation module for python
Author-email: ilco <martinii.fun@gmail.com>
License-Expression: MIT
Project-URL: Homepage, https://github.com/pypa/sampleproject
Project-URL: Issues, https://github.com/pypa/sampleproject/issues
Classifier: Programming Language :: Python :: 3
Classifier: Operating System :: Microsoft :: Windows :: Windows 11
Requires-Python: >=3.9
License-File: LICENSE
Dynamic: license-file
